arg_services/__init__.py
arg_services/cbr/__init__.py
arg_services/cbr/v1beta/__init__.py
arg_services/cbr/v1beta/adaptation_pb2.py
arg_services/cbr/v1beta/adaptation_pb2.pyi
arg_services/cbr/v1beta/adaptation_pb2_grpc.py
arg_services/cbr/v1beta/adaptation_pb2_grpc.pyi
arg_services/cbr/v1beta/casebase_pb2.py
arg_services/cbr/v1beta/casebase_pb2.pyi
arg_services/cbr/v1beta/casebase_pb2_grpc.py
arg_services/cbr/v1beta/casebase_pb2_grpc.pyi
arg_services/cbr/v1beta/model_pb2.py
arg_services/cbr/v1beta/model_pb2.pyi
arg_services/cbr/v1beta/model_pb2_grpc.py
arg_services/cbr/v1beta/model_pb2_grpc.pyi
arg_services/cbr/v1beta/retrieval_pb2.py
arg_services/cbr/v1beta/retrieval_pb2.pyi
arg_services/cbr/v1beta/retrieval_pb2_grpc.py
arg_services/cbr/v1beta/retrieval_pb2_grpc.pyi
arg_services/graph/__init__.py
arg_services/graph/v1/__init__.py
arg_services/graph/v1/graph_pb2.py
arg_services/graph/v1/graph_pb2.pyi
arg_services/graph/v1/graph_pb2_grpc.py
arg_services/graph/v1/graph_pb2_grpc.pyi
arg_services/mining/__init__.py
arg_services/mining/v1beta/__init__.py
arg_services/mining/v1beta/adu_pb2.py
arg_services/mining/v1beta/adu_pb2.pyi
arg_services/mining/v1beta/adu_pb2_grpc.py
arg_services/mining/v1beta/adu_pb2_grpc.pyi
arg_services/mining/v1beta/entailment_pb2.py
arg_services/mining/v1beta/entailment_pb2.pyi
arg_services/mining/v1beta/entailment_pb2_grpc.py
arg_services/mining/v1beta/entailment_pb2_grpc.pyi
arg_services/mining/v1beta/graph_construction_pb2.py
arg_services/mining/v1beta/graph_construction_pb2.pyi
arg_services/mining/v1beta/graph_construction_pb2_grpc.py
arg_services/mining/v1beta/graph_construction_pb2_grpc.pyi
arg_services/mining/v1beta/major_claim_pb2.py
arg_services/mining/v1beta/major_claim_pb2.pyi
arg_services/mining/v1beta/major_claim_pb2_grpc.py
arg_services/mining/v1beta/major_claim_pb2_grpc.pyi
arg_services/mining/v1beta/mining_pb2.py
arg_services/mining/v1beta/mining_pb2.pyi
arg_services/mining/v1beta/mining_pb2_grpc.py
arg_services-1.7.11.dist-info/licenses/LICENSE
arg_services-1.7.11.dist-info/METADATA
arg_services-1.7.11.dist-info/WHEEL
arg_services-1.7.11.dist-info/top_level.txt
arg_services-1.7.11.dist-info/RECORD
