Metadata-Version: 2.4
Name: arg-services
Version: 1.7.11
Summary: gRPC definitions for microservice-based argumentation machines
Author-email: Mirko Lenz <mirko@mirkolenz.com>
Requires-Python: >=3.10
License-File: LICENSE
Requires-Dist: grpcio-reflection<2,>=1
Requires-Dist: grpcio<2,>=1
Requires-Dist: protobuf<6,>=5
Requires-Dist: types-protobuf<6,>=5
Dynamic: license-file
